{
  "trainers": [
    {
      "id": "1",
      "nombres": "carlos",
      "apellidos": "rueda",
      "especialidad": "backend java"
    },
    {
      "id": "2",
      "nombres": "miguel",
      "apellidos": "ruiz",
      "especialidad": "javascript",
      "sexo": "m",
      "edad": "25"
    }
  ],
  "campers": [
    {
      "id": "1",
      "nombres": "luis",
      "apellidos": "ariza",
      "trainerId": "1"
    },
    {
      "id": "2",
      "nombres": "hader",
      "apellidos": "cabrera",
      "trainerId": "2"
    }
  ],
  "salones": []
}